{"cameraMode":{"drawMode":0,"name":"Shaded","section":"Shading Mode"},"sceneLighting":true,"audioPlay":false,"sceneViewState":{"showFog":true,"showMaterialUpdate":false,"showSkybox":true,"showFlares":true,"showImageEffects":true,"showParticleSystems":true},"in2DMode":false,"pivot":{"x":915.410400390625,"y":483.5335693359375,"z":4.2308349609375},"rotation":{"x":0.03780050948262215,"y":-0.0030023795552551748,"z":0.00011330691631883383,"w":0.9992843270301819},"size":440.629638671875,"orthographic":false}